MANIFEST.in
distribute_setup.py
setup.py
graphit/__init__.py
graphit/cli.py
graphit/config.py
graphit/data.py
graphit/graph.py
graphit/interface.py
graphit/util.py
graphit.io.egg-info/PKG-INFO
graphit.io.egg-info/SOURCES.txt
graphit.io.egg-info/dependency_links.txt
graphit.io.egg-info/entry_points.txt
graphit.io.egg-info/requires.txt
graphit.io.egg-info/top_level.txt
graphit.io.egg-info/zip-safe