Metadata-Version: 1.0
Name: graphit.io
Version: 0.0.6
Summary: Graphit.io Graphing API library
Home-page: https://graphit.io/
Author: Eric Seifert
Author-email: seiferteric@gmail.com
License: UNKNOWN
Keywords: graphit graph Graphit.io
Platform: UNKNOWN
